asta_s_eu/scraping/kleinanzeigen_de/__init__.py
asta_s_eu/scraping/kleinanzeigen_de/ciur.py
asta_s_eu/scraping/kleinanzeigen_de/cli.py
asta_s_eu/scraping/kleinanzeigen_de/defaults.py
asta_s_eu/scraping/kleinanzeigen_de/irequests.py
asta_s_eu/scraping/kleinanzeigen_de/logging.yaml
asta_s_eu/scraping/kleinanzeigen_de/py.typed
asta_s_eu/scraping/kleinanzeigen_de/the_config.py
asta_s_eu/scraping/kleinanzeigen_de/typing.py
asta_s_eu_scraping_kleinanzeigen_de-0.2.1.dist-info/METADATA
asta_s_eu_scraping_kleinanzeigen_de-0.2.1.dist-info/WHEEL
asta_s_eu_scraping_kleinanzeigen_de-0.2.1.dist-info/entry_points.txt
asta_s_eu_scraping_kleinanzeigen_de-0.2.1.dist-info/top_level.txt
asta_s_eu_scraping_kleinanzeigen_de-0.2.1.dist-info/RECORD
