Metadata-Version: 2.4
Name: asta-s-eu-scraping-kleinanzeigen-de
Version: 0.2.1
Author-email: Andrei Danciuc <python.ciur@gmail.com>
License-Expression: MIT
Requires-Python: ==3.13.2
Requires-Dist: asta-s-eu-scraping-core[otel]==0.0.6
Provides-Extra: dev
Requires-Dist: asta-s-eu-scraping-core[dev,otel]==0.0.6; extra == "dev"
Provides-Extra: otel
Requires-Dist: opentelemetry-distro; extra == "otel"
Requires-Dist: opentelemetry-exporter-otlp; extra == "otel"
